{"version":"3.7.1","examples":[{"id":"./spec/features/song_form_spec.rb[1:1]","description":"creates a song on submit","full_description":"the song form creates a song on submit","status":"passed","file_path":"./spec/features/song_form_spec.rb","line_number":5,"run_time":0.183999,"pending_message":null},{"id":"./spec/features/song_form_spec.rb[1:2]","description":"creates a song with an artist","full_description":"the song form creates a song with an artist","status":"passed","file_path":"./spec/features/song_form_spec.rb","line_number":12,"run_time":0.043264,"pending_message":null},{"id":"./spec/features/song_form_spec.rb[1:3]","description":"creates a song with a genre","full_description":"the song form creates a song with a genre","status":"passed","file_path":"./spec/features/song_form_spec.rb","line_number":21,"run_time":0.031122,"pending_message":null},{"id":"./spec/features/song_form_spec.rb[1:4]","description":"creates a song with notes","full_description":"the song form creates a song with notes","status":"passed","file_path":"./spec/features/song_form_spec.rb","line_number":30,"run_time":0.035659,"pending_message":null},{"id":"./spec/models/song_spec.rb[1:1:1]","description":"sets the genre to the genre of the specified name","full_description":"Song genre_name= sets the genre to the genre of the specified name","status":"passed","file_path":"./spec/models/song_spec.rb","line_number":5,"run_time":0.00127,"pending_message":null},{"id":"./spec/models/song_spec.rb[1:2:1]","description":"returns the genre name","full_description":"Song genre_name returns the genre name","status":"passed","file_path":"./spec/models/song_spec.rb","line_number":13,"run_time":0.001105,"pending_message":null},{"id":"./spec/models/song_spec.rb[1:3:1]","description":"sets the artist to the artist of the specified name","full_description":"Song artist_name= sets the artist to the artist of the specified name","status":"passed","file_path":"./spec/models/song_spec.rb","line_number":21,"run_time":0.004036,"pending_message":null},{"id":"./spec/models/song_spec.rb[1:4:1]","description":"returns the artist name","full_description":"Song artist_name returns the artist name","status":"passed","file_path":"./spec/models/song_spec.rb","line_number":29,"run_time":0.004637,"pending_message":null},{"id":"./spec/models/song_spec.rb[1:5:1]","description":"returns the content of all notes as an array","full_description":"Song note_contents returns the content of all notes as an array","status":"passed","file_path":"./spec/models/song_spec.rb","line_number":37,"run_time":0.00156,"pending_message":null},{"id":"./spec/models/song_spec.rb[1:6:1]","description":"sets notes for a song","full_description":"Song note_contents= sets notes for a song","status":"passed","file_path":"./spec/models/song_spec.rb","line_number":45,"run_time":0.001743,"pending_message":null},{"id":"./spec/models/song_spec.rb[1:6:2]","description":"adds to existing notes","full_description":"Song note_contents= adds to existing notes","status":"passed","file_path":"./spec/models/song_spec.rb","line_number":51,"run_time":0.002373,"pending_message":null},{"id":"./spec/models/song_spec.rb[1:6:3]","description":"ignores blank notes","full_description":"Song note_contents= ignores blank notes","status":"passed","file_path":"./spec/models/song_spec.rb","line_number":63,"run_time":0.001728,"pending_message":null}],"summary":{"duration":0.316738,"example_count":12,"failure_count":0,"pending_count":0,"errors_outside_of_examples_count":0},"summary_line":"12 examples, 0 failures"}